zensols/relpo/__init__.py
zensols/relpo/app.py
zensols/relpo/cli.py
zensols/relpo/doc.py
zensols/relpo/domain.py
zensols/relpo/envdist.py
zensols/relpo/install_env.sh
zensols/relpo/project.py
zensols/relpo/repo.py
zensols_relpo-0.0.11.dist-info/METADATA
zensols_relpo-0.0.11.dist-info/WHEEL
zensols_relpo-0.0.11.dist-info/entry_points.txt
zensols_relpo-0.0.11.dist-info/licenses/LICENSE.md
zensols_relpo-0.0.11.dist-info/RECORD
