Metadata-Version: 2.3
Name: zensols_relpo
Version: 0.0.11
Summary: A Python project release with Git integration.
Project-URL: Homepage, https://github.com/plandes/relpo
Project-URL: Documentation, https://plandes.github.io/relpo
Project-URL: Repository, https://github.com/plandes/relpo.git
Project-URL: Issues, https://github.com/plandes/relpo/issues
Project-URL: Changelog, https://github.com/plandes/relpo/blob/master/CHANGELOG.md
Author-email: Paul Landes <landes@mailc.net>
License: MIT
Keywords: build,utility
Requires-Python: <3.15,>=3.13
Requires-Dist: btd-sphinx-graphviz
Requires-Dist: btd-sphinx-inheritance-diagram
Requires-Dist: furo
Requires-Dist: gitdb2~=2.0.3
Requires-Dist: gitpython~=3.1.29
Requires-Dist: jinja2>=3.1
Requires-Dist: plac~=1.4.5
Requires-Dist: pyyaml~=6.0.1
Requires-Dist: recommonmark
Requires-Dist: rst2pdf
Requires-Dist: sphinx-autodoc-typehints
Requires-Dist: sphinx-codeautolink
Requires-Dist: sphinx-copybutton
Requires-Dist: sphinx~=7.4.7
Requires-Dist: tomlkit~=0.13.2
Requires-Dist: tqdm
Requires-Dist: twine~=6.1.0
Requires-Dist: zstandard
